apache_analyser_package/__init__.py
apache_analyser_package/apache_analyser.py
apache_analyser-1.0.0.dist-info/LICENSE
apache_analyser-1.0.0.dist-info/METADATA
apache_analyser-1.0.0.dist-info/WHEEL
apache_analyser-1.0.0.dist-info/top_level.txt
apache_analyser-1.0.0.dist-info/RECORD
