Metadata-Version: 2.1
Name: apache-analyser
Version: 1.0.0
Summary: The main function of the project is to analyse the access log file of an Apache server.
Home-page: https://github.com/Zac-not-Zack/apache_analyser
Author: Wong Hoe Ziet & Adam Bin Azmi
Author-email: wonghz6071@gmail.com
License: UNKNOWN
Project-URL: Bug Tracker, https://github.com/pypa/sampleproject/issues
Platform: UNKNOWN
Classifier: Programming Language :: Python :: 3
Classifier: License :: OSI Approved :: MIT License
Classifier: Operating System :: OS Independent
Requires-Python: >=3.6
License-File: LICENSE
